Workbook

Sheet Instrucciones
A1: Control de Ventas y Publicidad
A2: Plantilla para tu tienda online: calcula márgenes, organiza tus páginas de producto y controla tus movimientos
A4: CÓMO USARLA
A5: 1. Calculadora | B5: Mete precio, costo, flete y comisiones de UN producto. Te dice tu utilidad, margen, cuánto puedes gastar en publicidad por venta (CPA) y el ROAS mínimo para no perder.
A6: 2. Productos | B6: Una fila por cada página/producto que publiques: estado, link, precio, costos. Calcula solo el margen y el CPA máximo.
A7: 3. Movimientos | B7: Anota cada venta, gasto de publicidad, flete, compra de mercancía, devolución, etc. Todo se suma solo.
A8: 4. Publicidad | B8: Registra tus campañas (Meta, TikTok, Google). Calcula CTR, CPC, CPA, ROAS y si ganas o pierdes.
A9: 5. Resumen | B9: Panel con tus totales y la utilidad por producto. No necesitas escribir nada aquí.
A10: COLORES
A11: Celda amarilla con letra azul | B11: Aquí SÍ escribes. Todo lo demás son fórmulas: no lo borres.
A12: Filas de ejemplo | B12: Cada hoja trae filas de ejemplo (productos y datos inventados). Bórralas / sustitúyelas por las tuyas.
A13: MONEDA | B13: Los formatos usan el signo $. Puedes usar tu moneda; las fórmulas no cambian.

Sheet Resumen
A1: Resumen general
A2: Se actualiza solo con lo que anotes en Movimientos y Publicidad.
A4: TOTALES (Movimientos)
A5: Ventas (ingresos) | B5: =SUM(Movimientos!$E$5:$E$504) -> 79.98
A6: Compra de mercancía | B6: =SUMIFS(Movimientos!$F$5:$F$504,Movimientos!$B$5:$B$504,"Compra de mercancía") -> 240
A7: Publicidad | B7: =SUMIFS(Movimientos!$F$5:$F$504,Movimientos!$B$5:$B$504,"Publicidad") -> 15
A8: Fletes | B8: =SUMIFS(Movimientos!$F$5:$F$504,Movimientos!$B$5:$B$504,"Flete") -> 5
A9: Devoluciones | B9: =SUMIFS(Movimientos!$F$5:$F$504,Movimientos!$B$5:$B$504,"Devolución") -> 0
A10: Comisiones | B10: =SUMIFS(Movimientos!$F$5:$F$504,Movimientos!$B$5:$B$504,"Comisión") -> 0
A11: Herramientas / apps | B11: =SUMIFS(Movimientos!$F$5:$F$504,Movimientos!$B$5:$B$504,"Herramientas/Apps") -> 0
A12: Otros gastos | B12: =SUMIFS(Movimientos!$F$5:$F$504,Movimientos!$B$5:$B$504,"Otro") -> 0
A13: Total gastos | B13: =SUM(Movimientos!$F$5:$F$504) -> 260
A14: UTILIDAD (ingresos – gastos) | B14: =B5-B13 -> -180.02
A15: Margen sobre ventas % | B15: =IF(B5=0,0,B14/B5) -> -2.2508127
A16: Publicidad como % de ventas | B16: =IF(B5=0,0,B7/B5) -> 0.18754689
A17: ROAS real (ventas / publicidad) | B17: =IF(B7=0,0,B5/B7) -> 5.332
A20: POR PRODUCTO
A21: Producto | B21: Ingresos | C21: Gastos totales | D21: Publicidad | E21: Utilidad | F21: Margen % | G21: Estado de la página
A22: =IF(Productos!B5="","",Productos!B5) -> Masajeador de cuello | B22: =IF(A22="","",SUMIFS(Movimientos!$E$5:$E$504,Movimientos!$C$5:$C$504,A22)) -> 79.98 | C22: =IF(A22="","",SUMIFS(Movimientos!$F$5:$F$504,Movimientos!$C$5:$C$504,A22)) -> 260 | D22: =IF(A22="","",SUMIFS(Movimientos!$F$5:$F$504,Movimientos!$C$5:$C$504,A22,Movimientos!$B$5:$B$504,"Publicidad")) -> 15 | E22: =IF(A22="","",B22-C22) -> -180.02 | F22: =IF(OR(A22="",B22=0),"",E22/B22) -> -2.2508127 | G22: =IF(A22="","",Productos!D5) -> Publicada
A23: =IF(Productos!B6="","",Productos!B6) -> Lámpara LED lunar | B23: =IF(A23="","",SUMIFS(Movimientos!$E$5:$E$504,Movimientos!$C$5:$C$504,A23)) -> 0 | C23: =IF(A23="","",SUMIFS(Movimientos!$F$5:$F$504,Movimientos!$C$5:$C$504,A23)) -> 0 | D23: =IF(A23="","",SUMIFS(Movimientos!$F$5:$F$504,Movimientos!$C$5:$C$504,A23,Movimientos!$B$5:$B$504,"Publicidad")) -> 0 | E23: =IF(A23="","",B23-C23) -> 0 | F23: =IF(OR(A23="",B23=0),"",E23/B23) | G23: =IF(A23="","",Productos!D6) -> En creación
A24: =IF(Productos!B7="","",Productos!B7) -> Organizador de cocina | B24: =IF(A24="","",SUMIFS(Movimientos!$E$5:$E$504,Movimientos!$C$5:$C$504,A24)) -> 0 | C24: =IF(A24="","",SUMIFS(Movimientos!$F$5:$F$504,Movimientos!$C$5:$C$504,A24)) -> 0 | D24: =IF(A24="","",SUMIFS(Movimientos!$F$5:$F$504,Movimientos!$C$5:$C$504,A24,Movimientos!$B$5:$B$504,"Publicidad")) -> 0 | E24: =IF(A24="","",B24-C24) -> 0 | F24: =IF(OR(A24="",B24=0),"",E24/B24) | G24: =IF(A24="","",Productos!D7) -> Idea
A25: =IF(Productos!B8="","",Productos!B8) | B25: =IF(A25="","",SUMIFS(Movimientos!$E$5:$E$504,Movimientos!$C$5:$C$504,A25)) | C25: =IF(A25="","",SUMIFS(Movimientos!$F$5:$F$504,Movimientos!$C$5:$C$504,A25)) | D25: =IF(A25="","",SUMIFS(Movimientos!$F$5:$F$504,Movimientos!$C$5:$C$504,A25,Movimientos!$B$5:$B$504,"Publicidad")) | E25: =IF(A25="","",B25-C25) | F25: =IF(OR(A25="",B25=0),"",E25/B25) | G25: =IF(A25="","",Productos!D8)
A26: =IF(Productos!B9="","",Productos!B9) | B26: =IF(A26="","",SUMIFS(Movimientos!$E$5:$E$504,Movimientos!$C$5:$C$504,A26)) | C26: =IF(A26="","",SUMIFS(Movimientos!$F$5:$F$504,Movimientos!$C$5:$C$504,A26)) | D26: =IF(A26="","",SUMIFS(Movimientos!$F$5:$F$504,Movimientos!$C$5:$C$504,A26,Movimientos!$B$5:$B$504,"Publicidad")) | E26: =IF(A26="","",B26-C26) | F26: =IF(OR(A26="",B26=0),"",E26/B26) | G26: =IF(A26="","",Productos!D9)
A27: =IF(Productos!B10="","",Productos!B10) | B27: =IF(A27="","",SUMIFS(Movimientos!$E$5:$E$504,Movimientos!$C$5:$C$504,A27)) | C27: =IF(A27="","",SUMIFS(Movimientos!$F$5:$F$504,Movimientos!$C$5:$C$504,A27)) | D27: =IF(A27="","",SUMIFS(Movimientos!$F$5:$F$504,Movimientos!$C$5:$C$504,A27,Movimientos!$B$5:$B$504,"Publicidad")) | E27: =IF(A27="","",B27-C27) | F27: =IF(OR(A27="",B27=0),"",E27/B27) | G27: =IF(A27="","",Productos!D10)
A28: =IF(Productos!B11="","",Productos!B11) | B28: =IF(A28="","",SUMIFS(Movimientos!$E$5:$E$504,Movimientos!$C$5:$C$504,A28)) | C28: =IF(A28="","",SUMIFS(Movimientos!$F$5:$F$504,Movimientos!$C$5:$C$504,A28)) | D28: =IF(A28="","",SUMIFS(Movimientos!$F$5:$F$504,Movimientos!$C$5:$C$504,A28,Movimientos!$B$5:$B$504,"Publicidad")) | E28: =IF(A28="","",B28-C28) | F28: =IF(OR(A28="",B28=0),"",E28/B28) | G28: =IF(A28="","",Productos!D11)
A29: =IF(Productos!B12="","",Productos!B12) | B29: =IF(A29="","",SUMIFS(Movimientos!$E$5:$E$504,Movimientos!$C$5:$C$504,A29)) | C29: =IF(A29="","",SUMIFS(Movimientos!$F$5:$F$504,Movimientos!$C$5:$C$504,A29)) | D29: =IF(A29="","",SUMIFS(Movimientos!$F$5:$F$504,Movimientos!$C$5:$C$504,A29,Movimientos!$B$5:$B$504,"Publicidad")) | E29: =IF(A29="","",B29-C29) | F29: =IF(OR(A29="",B29=0),"",E29/B29) | G29: =IF(A29="","",Productos!D12)
A30: =IF(Productos!B13="","",Productos!B13) | B30: =IF(A30="","",SUMIFS(Movimientos!$E$5:$E$504,Movimientos!$C$5:$C$504,A30)) | C30: =IF(A30="","",SUMIFS(Movimientos!$F$5:$F$504,Movimientos!$C$5:$C$504,A30)) | D30: =IF(A30="","",SUMIFS(Movimientos!$F$5:$F$504,Movimientos!$C$5:$C$504,A30,Movimientos!$B$5:$B$504,"Publicidad")) | E30: =IF(A30="","",B30-C30) | F30: =IF(OR(A30="",B30=0),"",E30/B30) | G30: =IF(A30="","",Productos!D13)
A31: =IF(Productos!B14="","",Productos!B14) | B31: =IF(A31="","",SUMIFS(Movimientos!$E$5:$E$504,Movimientos!$C$5:$C$504,A31)) | C31: =IF(A31="","",SUMIFS(Movimientos!$F$5:$F$504,Movimientos!$C$5:$C$504,A31)) | D31: =IF(A31="","",SUMIFS(Movimientos!$F$5:$F$504,Movimientos!$C$5:$C$504,A31,Movimientos!$B$5:$B$504,"Publicidad")) | E31: =IF(A31="","",B31-C31) | F31: =IF(OR(A31="",B31=0),"",E31/B31) | G31: =IF(A31="","",Productos!D14)
A32: =IF(Productos!B15="","",Productos!B15) | B32: =IF(A32="","",SUMIFS(Movimientos!$E$5:$E$504,Movimientos!$C$5:$C$504,A32)) | C32: =IF(A32="","",SUMIFS(Movimientos!$F$5:$F$504,Movimientos!$C$5:$C$504,A32)) | D32: =IF(A32="","",SUMIFS(Movimientos!$F$5:$F$504,Movimientos!$C$5:$C$504,A32,Movimientos!$B$5:$B$504,"Publicidad")) | E32: =IF(A32="","",B32-C32) | F32: =IF(OR(A32="",B32=0),"",E32/B32) | G32: =IF(A32="","",Productos!D15)
A33: =IF(Productos!B16="","",Productos!B16) | B33: =IF(A33="","",SUMIFS(Movimientos!$E$5:$E$504,Movimientos!$C$5:$C$504,A33)) | C33: =IF(A33="","",SUMIFS(Movimientos!$F$5:$F$504,Movimientos!$C$5:$C$504,A33)) | D33: =IF(A33="","",SUMIFS(Movimientos!$F$5:$F$504,Movimientos!$C$5:$C$504,A33,Movimientos!$B$5:$B$504,"Publicidad")) | E33: =IF(A33="","",B33-C33) | F33: =IF(OR(A33="",B33=0),"",E33/B33) | G33: =IF(A33="","",Productos!D16)
... A51: =IF(Productos!B34="","",Productos!B34) | B51: =IF(A51="","",SUMIFS(Movimientos!$E$5:$E$504,Movimientos!$C$5:$C$504,A51)) | C51: =IF(A51="","",SUMIFS(Movimientos!$F$5:$F$504,Movimientos!$C$5:$C$504,A51)) | D51: =IF(A51="","",SUMIFS(Movimientos!$F$5:$F$504,Movimientos!$C$5:$C$504,A51,Movimientos!$B$5:$B$504,"Publicidad")) | E51: =IF(A51="","",B51-C51) | F51: =IF(OR(A51="",B51=0),"",E51/B51) | G51: =IF(A51="","",Productos!D34)

Sheet Calculadora
A1: Calculadora de ganancias
A2: Escribe en las celdas amarillas. Todo lo demás se calcula solo.
A4: 1) DATOS DE TU PRODUCTO (por unidad)
A5: Precio de venta | B5: 39.99 | C5: Lo que paga tu cliente
A6: Costo del producto | B6: 12 | C6: Lo que te cuesta a ti
A7: Flete / envío al cliente | B7: 5 | C7: Costo de envío que pagas tú
A8: Empaque / otros costos | B8: 0.5 | C8: Caja, etiqueta, bolsa...
A9: Comisión pasarela de pago % | B9: 0.04 | C9: Shopify Payments/PayPal/Stripe ≈ 3–5%
A10: Comisión fija por transacción | B10: 0.3 | C10: Ej. $0.30 por pago con tarjeta (pon 0 si no aplica)
A11: % de devoluciones / cancelaciones | B11: 0.05 | C11: Estima el % de pedidos que se devuelven
A12: Costo de devolución (por pedido devuelto) | B12: 5 | C12: Flete perdido + producto dañado
A14: 2) RESULTADO POR VENTA
A15: Comisión pasarela ($) | B15: =B5*B9+B10 -> 1.8996
A16: Costo esperado por devoluciones ($) | B16: =B11*B12 -> 0.25
A17: Costos totales (sin publicidad) | B17: =B6+B7+B8+B15+B16 -> 19.6496
A18: Utilidad ANTES de publicidad | B18: =B5-B17 -> 20.3404
A19: Margen antes de publicidad % | B19: =IF(B5=0,0,B18/B5) -> 0.50863716
A20: Markup (utilidad / costo del producto) | B20: =IF(B6=0,0,B18/B6) -> 1.6950333
A22: 3) ¿CUÁNTO PUEDO GASTAR EN PUBLICIDAD?
A23: Margen de ganancia que quiero conservar % (neto) | B23: 0.2 | C23: Ej. 20% del precio de venta como ganancia final
A24: CPA máximo (punto de equilibrio) | B24: =MAX(B18,0) -> 20.3404 | C24: Si pagas más que esto por cada venta, PIERDES dinero
A25: ROAS mínimo (punto de equilibrio) | B25: =IF(B18<=0,"No hay margen",B5/B18) -> 1.966038 | C25: Tu campaña debe superar este ROAS
A26: CPA objetivo (con la ganancia que quiero) | B26: =MAX(B18-B5*B23,0) -> 12.3424 | C26: Cuánto gastar por venta para ganar lo que quieres
A27: ROAS objetivo | B27: =IF(B26<=0,"No hay margen",B5/B26) -> 3.2400506 | C27: ROAS que necesitas para tu ganancia deseada
A28: Ganancia final por venta (con CPA objetivo) | B28: =B18-B26 -> 7.998
A30: 4) PROYECCIÓN DEL MES
A31: Presupuesto de publicidad del mes | B31: 300
A32: CPA que esperas conseguir (costo por venta) | B32: 12
A33: Ventas estimadas (unidades) | B33: =IF(B32<=0,0,B31/B32) -> 25
A34: Ingresos estimados | B34: =B33*B5 -> 999.75
A35: Utilidad antes de publicidad | B35: =B33*B18 -> 508.51
A36: Utilidad NETA (después de publicidad) | B36: =B35-B31 -> 208.51
A37: ROAS esperado | B37: =IF(B31=0,0,B34/B31) -> 3.3325
A38: ROI (utilidad neta / publicidad) | B38: =IF(B31=0,0,B36/B31) -> 0.69503333
A39: Presupuesto diario sugerido (30 días) | B39: =B31/30 -> 10
A41: Fuentes de los supuestos: todos los valores de ejemplo son inventados por mí; sustitúyelos por los de tu proveedor, tu pasarela y tus campañas reales.

Sheet Productos
A1: Mis páginas / productos
A2: Una fila por página publicada. Amarillo = tú escribes. Margen y CPA máximo se calculan solos.
A4: # | B4: Producto | C4: Link de la página | D4: Estado | E4: Fecha publicación | F4: Precio venta | G4: Costo producto | H4: Flete / envío | I4: Comisión pasarela % | J4: Utilidad antes de publicidad | K4: Margen % | L4: CPA máximo (punto de equilibrio) | M4: ROAS mínimo | N4: Plataforma de anuncios | O4: Presupuesto diario | P4: Notas / siguiente paso
A5: 1 | B5: Masajeador de cuello | C5: https://mitienda.com/masajeador | D5: Publicada | E5: 46285 | F5: 39.99 | G5: 12 | H5: 5 | I5: 0.04 | J5: =IF(F5="","",F5-G5-H5-F5*I5) -> 21.3904 | K5: =IF(OR(F5="",F5=0),"",J5/F5) -> 0.53489372 | L5: =IF(J5="","",MAX(J5,0)) -> 21.3904 | M5: =IF(OR(J5="",J5<=0),"",F5/J5) -> 1.8695303 | N5: Meta | O5: 15 | P5: Probar video UGC nuevo
A6: 2 | B6: Lámpara LED lunar | C6: https://mitienda.com/lampara | D6: En creación | F6: 29.99 | G6: 8 | H6: 4 | I6: 0.04 | J6: =IF(F6="","",F6-G6-H6-F6*I6) -> 16.7904 | K6: =IF(OR(F6="",F6=0),"",J6/F6) -> 0.55986662 | L6: =IF(J6="","",MAX(J6,0)) -> 16.7904 | M6: =IF(OR(J6="",J6<=0),"",F6/J6) -> 1.7861397 | N6: TikTok | O6: 10 | P6: Falta generar imágenes
A7: 3 | B7: Organizador de cocina | D7: Idea | F7: 24.99 | G7: 6 | H7: 4.5 | I7: 0.04 | J7: =IF(F7="","",F7-G7-H7-F7*I7) -> 13.4904 | K7: =IF(OR(F7="",F7=0),"",J7/F7) -> 0.53983193 | L7: =IF(J7="","",MAX(J7,0)) -> 13.4904 | M7: =IF(OR(J7="",J7<=0),"",F7/J7) -> 1.8524284 | O7: 0 | P7: Investigar competencia
A8: 4 | J8: =IF(F8="","",F8-G8-H8-F8*I8) | K8: =IF(OR(F8="",F8=0),"",J8/F8) | L8: =IF(J8="","",MAX(J8,0)) | M8: =IF(OR(J8="",J8<=0),"",F8/J8)
A9: 5 | J9: =IF(F9="","",F9-G9-H9-F9*I9) | K9: =IF(OR(F9="",F9=0),"",J9/F9) | L9: =IF(J9="","",MAX(J9,0)) | M9: =IF(OR(J9="",J9<=0),"",F9/J9)
A10: 6 | J10: =IF(F10="","",F10-G10-H10-F10*I10) | K10: =IF(OR(F10="",F10=0),"",J10/F10) | L10: =IF(J10="","",MAX(J10,0)) | M10: =IF(OR(J10="",J10<=0),"",F10/J10)
A11: 7 | J11: =IF(F11="","",F11-G11-H11-F11*I11) | K11: =IF(OR(F11="",F11=0),"",J11/F11) | L11: =IF(J11="","",MAX(J11,0)) | M11: =IF(OR(J11="",J11<=0),"",F11/J11)
A12: 8 | J12: =IF(F12="","",F12-G12-H12-F12*I12) | K12: =IF(OR(F12="",F12=0),"",J12/F12) | L12: =IF(J12="","",MAX(J12,0)) | M12: =IF(OR(J12="",J12<=0),"",F12/J12)
A13: 9 | J13: =IF(F13="","",F13-G13-H13-F13*I13) | K13: =IF(OR(F13="",F13=0),"",J13/F13) | L13: =IF(J13="","",MAX(J13,0)) | M13: =IF(OR(J13="",J13<=0),"",F13/J13)
A14: 10 | J14: =IF(F14="","",F14-G14-H14-F14*I14) | K14: =IF(OR(F14="",F14=0),"",J14/F14) | L14: =IF(J14="","",MAX(J14,0)) | M14: =IF(OR(J14="",J14<=0),"",F14/J14)
A15: 11 | J15: =IF(F15="","",F15-G15-H15-F15*I15) | K15: =IF(OR(F15="",F15=0),"",J15/F15) | L15: =IF(J15="","",MAX(J15,0)) | M15: =IF(OR(J15="",J15<=0),"",F15/J15)
A16: 12 | J16: =IF(F16="","",F16-G16-H16-F16*I16) | K16: =IF(OR(F16="",F16=0),"",J16/F16) | L16: =IF(J16="","",MAX(J16,0)) | M16: =IF(OR(J16="",J16<=0),"",F16/J16)
A17: 13 | J17: =IF(F17="","",F17-G17-H17-F17*I17) | K17: =IF(OR(F17="",F17=0),"",J17/F17) | L17: =IF(J17="","",MAX(J17,0)) | M17: =IF(OR(J17="",J17<=0),"",F17/J17)
A18: 14 | J18: =IF(F18="","",F18-G18-H18-F18*I18) | K18: =IF(OR(F18="",F18=0),"",J18/F18) | L18: =IF(J18="","",MAX(J18,0)) | M18: =IF(OR(J18="",J18<=0),"",F18/J18)
A19: 15 | J19: =IF(F19="","",F19-G19-H19-F19*I19) | K19: =IF(OR(F19="",F19=0),"",J19/F19) | L19: =IF(J19="","",MAX(J19,0)) | M19: =IF(OR(J19="",J19<=0),"",F19/J19)
... A34: 30 | J34: =IF(F34="","",F34-G34-H34-F34*I34) | K34: =IF(OR(F34="",F34=0),"",J34/F34) | L34: =IF(J34="","",MAX(J34,0)) | M34: =IF(OR(J34="",J34<=0),"",F34/J34)
A36: Nota: los precios, costos y comisión de los ejemplos son inventados. Comisión pasarela ≈ 4% es un valor típico (Shopify Payments/PayPal), cámbialo por el tuyo.

Sheet Movimientos
A1: Mis movimientos
A2: Anota cada ingreso y gasto. Ingreso = dinero que entra; Egreso = dinero que sale.
A4: Fecha | B4: Tipo | C4: Producto | D4: Descripción | E4: Ingreso | F4: Egreso | G4: Balance acumulado
A5: 46296 | B5: Venta | C5: Masajeador de cuello | D5: Pedido #1001 | E5: 39.99 | G5: =IF(AND(E5="",F5=""),"",SUM($E$5:E5)-SUM($F$5:F5)) -> 39.99
A6: 46296 | B6: Publicidad | C6: Masajeador de cuello | D6: Meta Ads - día 1 | F6: 15 | G6: =IF(AND(E6="",F6=""),"",SUM($E$5:E6)-SUM($F$5:F6)) -> 24.99
A7: 46297 | B7: Compra de mercancía | C7: Masajeador de cuello | D7: Lote 20 unidades | F7: 240 | G7: =IF(AND(E7="",F7=""),"",SUM($E$5:E7)-SUM($F$5:F7)) -> -215.01
A8: 46298 | B8: Flete | C8: Masajeador de cuello | D8: Envío pedido #1001 | F8: 5 | G8: =IF(AND(E8="",F8=""),"",SUM($E$5:E8)-SUM($F$5:F8)) -> -220.01
A9: 46299 | B9: Venta | C9: Masajeador de cuello | D9: Pedido #1002 | E9: 39.99 | G9: =IF(AND(E9="",F9=""),"",SUM($E$5:E9)-SUM($F$5:F9)) -> -180.02
G10: =IF(AND(E10="",F10=""),"",SUM($E$5:E10)-SUM($F$5:F10))
G11: =IF(AND(E11="",F11=""),"",SUM($E$5:E11)-SUM($F$5:F11))
G12: =IF(AND(E12="",F12=""),"",SUM($E$5:E12)-SUM($F$5:F12))
G13: =IF(AND(E13="",F13=""),"",SUM($E$5:E13)-SUM($F$5:F13))
G14: =IF(AND(E14="",F14=""),"",SUM($E$5:E14)-SUM($F$5:F14))
G15: =IF(AND(E15="",F15=""),"",SUM($E$5:E15)-SUM($F$5:F15))
G16: =IF(AND(E16="",F16=""),"",SUM($E$5:E16)-SUM($F$5:F16))
G17: =IF(AND(E17="",F17=""),"",SUM($E$5:E17)-SUM($F$5:F17))
G18: =IF(AND(E18="",F18=""),"",SUM($E$5:E18)-SUM($F$5:F18))
G19: =IF(AND(E19="",F19=""),"",SUM($E$5:E19)-SUM($F$5:F19))
G20: =IF(AND(E20="",F20=""),"",SUM($E$5:E20)-SUM($F$5:F20))
G21: =IF(AND(E21="",F21=""),"",SUM($E$5:E21)-SUM($F$5:F21))
... G504: =IF(AND(E504="",F504=""),"",SUM($E$5:E504)-SUM($F$5:F504))

Sheet Publicidad
A1: Control de campañas de publicidad
A2: Registra el rendimiento de cada campaña/día. CTR, CPC, CPA y ROAS se calculan solos.
A4: Fecha | B4: Producto | C4: Plataforma | D4: Campaña / anuncio | E4: Gasto | F4: Impresiones | G4: Clics | H4: Ventas (#) | I4: Ingresos por ventas | J4: CTR | K4: CPC | L4: CPA | M4: ROAS | N4: Resultado | O4: Decisión sugerida | Q4: IDEAS PARA TU PUBLICIDAD
A5: 46296 | B5: Masajeador de cuello | C5: Meta | D5: Video UGC 1 | E5: 15 | F5: 4200 | G5: 96 | H5: 2 | I5: 79.98 | J5: =IF(OR(F5="",F5=0),"",G5/F5) -> 0.022857143 | K5: =IF(OR(G5="",G5=0),"",E5/G5) -> 0.15625 | L5: =IF(OR(H5="",H5=0),"",E5/H5) -> 7.5 | M5: =IF(OR(E5="",E5=0),"",I5/E5) -> 5.332 | N5: =IF(E5="","",I5-E5) -> 64.98 | O5: =IF(E5="","",IF(E5<5,"Seguir probando",IF(M5="","",IF(M5>=3,"Escalar (subir presupuesto)",IF(M5>=1.5,"Optimizar creativo","Pausar o cambiar anuncio"))))) -> Escalar (subir presupuesto) | Q5: 1. Empieza con 3–5 videos cortos (UGC, demo del producto, antes/después) y mide cuál gana.
A6: 46297 | B6: Masajeador de cuello | C6: Meta | D6: Video UGC 1 | E6: 15 | F6: 3900 | G6: 70 | H6: 0 | I6: 0 | J6: =IF(OR(F6="",F6=0),"",G6/F6) -> 0.017948718 | K6: =IF(OR(G6="",G6=0),"",E6/G6) -> 0.21428571 | L6: =IF(OR(H6="",H6=0),"",E6/H6) | M6: =IF(OR(E6="",E6=0),"",I6/E6) -> 0 | N6: =IF(E6="","",I6-E6) -> -15 | O6: =IF(E6="","",IF(E6<5,"Seguir probando",IF(M6="","",IF(M6>=3,"Escalar (subir presupuesto)",IF(M6>=1.5,"Optimizar creativo","Pausar o cambiar anuncio"))))) -> Pausar o cambiar anuncio | Q6: 2. Prueba cada anuncio con 2–3x tu CPA máximo antes de decidir si sirve.
A7: 46298 | B7: Masajeador de cuello | C7: TikTok | D7: Demo 15s | E7: 12 | F7: 6100 | G7: 150 | H7: 1 | I7: 39.99 | J7: =IF(OR(F7="",F7=0),"",G7/F7) -> 0.024590164 | K7: =IF(OR(G7="",G7=0),"",E7/G7) -> 0.08 | L7: =IF(OR(H7="",H7=0),"",E7/H7) -> 12 | M7: =IF(OR(E7="",E7=0),"",I7/E7) -> 3.3325 | N7: =IF(E7="","",I7-E7) -> 27.99 | O7: =IF(E7="","",IF(E7<5,"Seguir probando",IF(M7="","",IF(M7>=3,"Escalar (subir presupuesto)",IF(M7>=1.5,"Optimizar creativo","Pausar o cambiar anuncio"))))) -> Escalar (subir presupuesto) | Q7: 3. Regla de la hoja: ROAS ≥ 3 escalar; 1.5–3 mejorar creativo; < 1.5 pausar.
J8: =IF(OR(F8="",F8=0),"",G8/F8) | K8: =IF(OR(G8="",G8=0),"",E8/G8) | L8: =IF(OR(H8="",H8=0),"",E8/H8) | M8: =IF(OR(E8="",E8=0),"",I8/E8) | N8: =IF(E8="","",I8-E8) | O8: =IF(E8="","",IF(E8<5,"Seguir probando",IF(M8="","",IF(M8>=3,"Escalar (subir presupuesto)",IF(M8>=1.5,"Optimizar creativo","Pausar o cambiar anuncio"))))) | Q8: 4. Escala subiendo el presupuesto 20–30% cada 2–3 días, no de golpe.
J9: =IF(OR(F9="",F9=0),"",G9/F9) | K9: =IF(OR(G9="",G9=0),"",E9/G9) | L9: =IF(OR(H9="",H9=0),"",E9/H9) | M9: =IF(OR(E9="",E9=0),"",I9/E9) | N9: =IF(E9="","",I9-E9) | O9: =IF(E9="","",IF(E9<5,"Seguir probando",IF(M9="","",IF(M9>=3,"Escalar (subir presupuesto)",IF(M9>=1.5,"Optimizar creativo","Pausar o cambiar anuncio"))))) | Q9: 5. Meta: segmentación amplia + buen creativo. TikTok: gancho en los primeros 3 segundos.
J10: =IF(OR(F10="",F10=0),"",G10/F10) | K10: =IF(OR(G10="",G10=0),"",E10/G10) | L10: =IF(OR(H10="",H10=0),"",E10/H10) | M10: =IF(OR(E10="",E10=0),"",I10/E10) | N10: =IF(E10="","",I10-E10) | O10: =IF(E10="","",IF(E10<5,"Seguir probando",IF(M10="","",IF(M10>=3,"Escalar (subir presupuesto)",IF(M10>=1.5,"Optimizar creativo","Pausar o cambiar anuncio"))))) | Q10: 6. Reutiliza los mejores anuncios con otro gancho/texto; guarda las reseñas de clientes.
J11: =IF(OR(F11="",F11=0),"",G11/F11) | K11: =IF(OR(G11="",G11=0),"",E11/G11) | L11: =IF(OR(H11="",H11=0),"",E11/H11) | M11: =IF(OR(E11="",E11=0),"",I11/E11) | N11: =IF(E11="","",I11-E11) | O11: =IF(E11="","",IF(E11<5,"Seguir probando",IF(M11="","",IF(M11>=3,"Escalar (subir presupuesto)",IF(M11>=1.5,"Optimizar creativo","Pausar o cambiar anuncio"))))) | Q11: 7. Activa remarketing (visitantes que no compraron) con 10–20% del presupuesto.
J12: =IF(OR(F12="",F12=0),"",G12/F12) | K12: =IF(OR(G12="",G12=0),"",E12/G12) | L12: =IF(OR(H12="",H12=0),"",E12/H12) | M12: =IF(OR(E12="",E12=0),"",I12/E12) | N12: =IF(E12="","",I12-E12) | O12: =IF(E12="","",IF(E12<5,"Seguir probando",IF(M12="","",IF(M12>=3,"Escalar (subir presupuesto)",IF(M12>=1.5,"Optimizar creativo","Pausar o cambiar anuncio"))))) | Q12: 8. Revisa que el ROAS mínimo (Calculadora) sea menor que tu ROAS real.
J13: =IF(OR(F13="",F13=0),"",G13/F13) | K13: =IF(OR(G13="",G13=0),"",E13/G13) | L13: =IF(OR(H13="",H13=0),"",E13/H13) | M13: =IF(OR(E13="",E13=0),"",I13/E13) | N13: =IF(E13="","",I13-E13) | O13: =IF(E13="","",IF(E13<5,"Seguir probando",IF(M13="","",IF(M13>=3,"Escalar (subir presupuesto)",IF(M13>=1.5,"Optimizar creativo","Pausar o cambiar anuncio")))))
J14: =IF(OR(F14="",F14=0),"",G14/F14) | K14: =IF(OR(G14="",G14=0),"",E14/G14) | L14: =IF(OR(H14="",H14=0),"",E14/H14) | M14: =IF(OR(E14="",E14=0),"",I14/E14) | N14: =IF(E14="","",I14-E14) | O14: =IF(E14="","",IF(E14<5,"Seguir probando",IF(M14="","",IF(M14>=3,"Escalar (subir presupuesto)",IF(M14>=1.5,"Optimizar creativo","Pausar o cambiar anuncio")))))
J15: =IF(OR(F15="",F15=0),"",G15/F15) | K15: =IF(OR(G15="",G15=0),"",E15/G15) | L15: =IF(OR(H15="",H15=0),"",E15/H15) | M15: =IF(OR(E15="",E15=0),"",I15/E15) | N15: =IF(E15="","",I15-E15) | O15: =IF(E15="","",IF(E15<5,"Seguir probando",IF(M15="","",IF(M15>=3,"Escalar (subir presupuesto)",IF(M15>=1.5,"Optimizar creativo","Pausar o cambiar anuncio")))))
J16: =IF(OR(F16="",F16=0),"",G16/F16) | K16: =IF(OR(G16="",G16=0),"",E16/G16) | L16: =IF(OR(H16="",H16=0),"",E16/H16) | M16: =IF(OR(E16="",E16=0),"",I16/E16) | N16: =IF(E16="","",I16-E16) | O16: =IF(E16="","",IF(E16<5,"Seguir probando",IF(M16="","",IF(M16>=3,"Escalar (subir presupuesto)",IF(M16>=1.5,"Optimizar creativo","Pausar o cambiar anuncio")))))
J17: =IF(OR(F17="",F17=0),"",G17/F17) | K17: =IF(OR(G17="",G17=0),"",E17/G17) | L17: =IF(OR(H17="",H17=0),"",E17/H17) | M17: =IF(OR(E17="",E17=0),"",I17/E17) | N17: =IF(E17="","",I17-E17) | O17: =IF(E17="","",IF(E17<5,"Seguir probando",IF(M17="","",IF(M17>=3,"Escalar (subir presupuesto)",IF(M17>=1.5,"Optimizar creativo","Pausar o cambiar anuncio")))))
J18: =IF(OR(F18="",F18=0),"",G18/F18) | K18: =IF(OR(G18="",G18=0),"",E18/G18) | L18: =IF(OR(H18="",H18=0),"",E18/H18) | M18: =IF(OR(E18="",E18=0),"",I18/E18) | N18: =IF(E18="","",I18-E18) | O18: =IF(E18="","",IF(E18<5,"Seguir probando",IF(M18="","",IF(M18>=3,"Escalar (subir presupuesto)",IF(M18>=1.5,"Optimizar creativo","Pausar o cambiar anuncio")))))
J19: =IF(OR(F19="",F19=0),"",G19/F19) | K19: =IF(OR(G19="",G19=0),"",E19/G19) | L19: =IF(OR(H19="",H19=0),"",E19/H19) | M19: =IF(OR(E19="",E19=0),"",I19/E19) | N19: =IF(E19="","",I19-E19) | O19: =IF(E19="","",IF(E19<5,"Seguir probando",IF(M19="","",IF(M19>=3,"Escalar (subir presupuesto)",IF(M19>=1.5,"Optimizar creativo","Pausar o cambiar anuncio")))))
J20: =IF(OR(F20="",F20=0),"",G20/F20) | K20: =IF(OR(G20="",G20=0),"",E20/G20) | L20: =IF(OR(H20="",H20=0),"",E20/H20) | M20: =IF(OR(E20="",E20=0),"",I20/E20) | N20: =IF(E20="","",I20-E20) | O20: =IF(E20="","",IF(E20<5,"Seguir probando",IF(M20="","",IF(M20>=3,"Escalar (subir presupuesto)",IF(M20>=1.5,"Optimizar creativo","Pausar o cambiar anuncio")))))
J21: =IF(OR(F21="",F21=0),"",G21/F21) | K21: =IF(OR(G21="",G21=0),"",E21/G21) | L21: =IF(OR(H21="",H21=0),"",E21/H21) | M21: =IF(OR(E21="",E21=0),"",I21/E21) | N21: =IF(E21="","",I21-E21) | O21: =IF(E21="","",IF(E21<5,"Seguir probando",IF(M21="","",IF(M21>=3,"Escalar (subir presupuesto)",IF(M21>=1.5,"Optimizar creativo","Pausar o cambiar anuncio")))))
J22: =IF(OR(F22="",F22=0),"",G22/F22) | K22: =IF(OR(G22="",G22=0),"",E22/G22) | L22: =IF(OR(H22="",H22=0),"",E22/H22) | M22: =IF(OR(E22="",E22=0),"",I22/E22) | N22: =IF(E22="","",I22-E22) | O22: =IF(E22="","",IF(E22<5,"Seguir probando",IF(M22="","",IF(M22>=3,"Escalar (subir presupuesto)",IF(M22>=1.5,"Optimizar creativo","Pausar o cambiar anuncio")))))
J23: =IF(OR(F23="",F23=0),"",G23/F23) | K23: =IF(OR(G23="",G23=0),"",E23/G23) | L23: =IF(OR(H23="",H23=0),"",E23/H23) | M23: =IF(OR(E23="",E23=0),"",I23/E23) | N23: =IF(E23="","",I23-E23) | O23: =IF(E23="","",IF(E23<5,"Seguir probando",IF(M23="","",IF(M23>=3,"Escalar (subir presupuesto)",IF(M23>=1.5,"Optimizar creativo","Pausar o cambiar anuncio")))))
J24: =IF(OR(F24="",F24=0),"",G24/F24) | K24: =IF(OR(G24="",G24=0),"",E24/G24) | L24: =IF(OR(H24="",H24=0),"",E24/H24) | M24: =IF(OR(E24="",E24=0),"",I24/E24) | N24: =IF(E24="","",I24-E24) | O24: =IF(E24="","",IF(E24<5,"Seguir probando",IF(M24="","",IF(M24>=3,"Escalar (subir presupuesto)",IF(M24>=1.5,"Optimizar creativo","Pausar o cambiar anuncio")))))
... J204: =IF(OR(F204="",F204=0),"",G204/F204) | K204: =IF(OR(G204="",G204=0),"",E204/G204) | L204: =IF(OR(H204="",H204=0),"",E204/H204) | M204: =IF(OR(E204="",E204=0),"",I204/E204) | N204: =IF(E204="","",I204-E204) | O204: =IF(E204="","",IF(E204<5,"Seguir probando",IF(M204="","",IF(M204>=3,"Escalar (subir presupuesto)",IF(M204>=1.5,"Optimizar creativo","Pausar o cambiar anuncio")))))
