Workbook

Sheet Candidatos
A1: Productos candidatos Q4 2026 - en pesos colombianos (COP)
A2: Costos y precios son SUPUESTOS míos basados en rangos de Dropi Colombia. Cámbialos (amarillo) por los de tu catálogo Dropi.
A3: No pude ver tu catálogo Dropi: reemplaza costo, flete y precio por los reales antes de decidir.
A5: # | B5: Producto (tipo a buscar en Dropi) | C5: Categoría | D5: Tipo | E5: Por qué en Q4 | F5: Costo Dropi (COP) | G5: Flete ida (COP) | H5: Precio de venta (COP) | I5: Comisión de recaudo contra entrega % | J5: % devolución / no entrega | K5: Costo por devolución (COP) (flete ida + vuelta) | L5: Utilidad antes de publicidad | M5: Margen % | N5: CPA máximo | O5: ROAS mínimo | P5: CPA base esperado (COP) | Q5: CPA Q4 (con alza) | R5: Utilidad neta por venta | S5: Margen neto % | T5: Veredicto | U5: ¿Resuelve un problema diario?
A6: 1 | B6: Proyector de galaxia / estrellas LED | C6: Hogar / regalo | D6: Viral | E6: Regalo visual, muy grabable en TikTok | F6: 29000 | G6: 15000 | H6: 109900 | I6: 0.035 | J6: 0.2 | K6: 30000 | L6: =H6-F6-G6-H6*I6-J6*K6 -> 56053.5 | M6: =IF(H6=0,0,L6/H6) -> 0.51004095 | N6: =MAX(L6,0) -> 56053.5 | O6: =IF(L6<=0,"Sin margen",H6/L6) -> 1.9606269 | P6: 29000 | Q6: =P6*(1+Plan_100K!$B$5) -> 46400 | R6: =L6-Q6 -> 9653.5 | S6: =IF(H6=0,0,R6/H6) -> 0.087838944 | T6: =IF(R6<=0,"NO: pierde dinero",IF(S6>=0.15,"SÍ: probar con fuerza","Probar con cuidado")) -> Probar con cuidado | U6: No (decoración)
A7: 2 | B7: Masajeador de cuello / espalda (EMS) | C7: Salud y bienestar | D7: Viral | E7: Dolor de cuello por computador y celular; regalo | F7: 35000 | G7: 15000 | H7: 129900 | I7: 0.035 | J7: 0.2 | K7: 30000 | L7: =H7-F7-G7-H7*I7-J7*K7 -> 69353.5 | M7: =IF(H7=0,0,L7/H7) -> 0.53389915 | N7: =MAX(L7,0) -> 69353.5 | O7: =IF(L7<=0,"Sin margen",H7/L7) -> 1.8730129 | P7: 35000 | Q7: =P7*(1+Plan_100K!$B$5) -> 56000 | R7: =L7-Q7 -> 13353.5 | S7: =IF(H7=0,0,R7/H7) -> 0.10279831 | T7: =IF(R7<=0,"NO: pierde dinero",IF(S7>=0.15,"SÍ: probar con fuerza","Probar con cuidado")) -> Probar con cuidado | U7: Sí
A8: 3 | B8: Audífonos Bluetooth (TWS) | C8: Tecnología | D8: Evergreen | E8: Regalo muy buscado en Black Friday; muy competido | F8: 26000 | G8: 15000 | H8: 94900 | I8: 0.035 | J8: 0.2 | K8: 30000 | L8: =H8-F8-G8-H8*I8-J8*K8 -> 44578.5 | M8: =IF(H8=0,0,L8/H8) -> 0.46974183 | N8: =MAX(L8,0) -> 44578.5 | O8: =IF(L8<=0,"Sin margen",H8/L8) -> 2.1288289 | P8: 32000 | Q8: =P8*(1+Plan_100K!$B$5) -> 51200 | R8: =L8-Q8 -> -6621.5 | S8: =IF(H8=0,0,R8/H8) -> -0.069773446 | T8: =IF(R8<=0,"NO: pierde dinero",IF(S8>=0.15,"SÍ: probar con fuerza","Probar con cuidado")) -> NO: pierde dinero | U8: Sí (pero margen mínimo)
A9: 4 | B9: Kit facial gua sha + rodillo + limpiador | C9: Belleza | D9: Viral | E9: Cuidado personal como regalo | F9: 16000 | G9: 15000 | H9: 79900 | I9: 0.035 | J9: 0.2 | K9: 30000 | L9: =H9-F9-G9-H9*I9-J9*K9 -> 40103.5 | M9: =IF(H9=0,0,L9/H9) -> 0.50192115 | N9: =MAX(L9,0) -> 40103.5 | O9: =IF(L9<=0,"Sin margen",H9/L9) -> 1.9923448 | P9: 22000 | Q9: =P9*(1+Plan_100K!$B$5) -> 35200 | R9: =L9-Q9 -> 4903.5 | S9: =IF(H9=0,0,R9/H9) -> 0.061370463 | T9: =IF(R9<=0,"NO: pierde dinero",IF(S9>=0.15,"SÍ: probar con fuerza","Probar con cuidado")) -> Probar con cuidado | U9: Parcial
A10: 5 | B10: Cepillo quitapelos autolimpiante mascotas | C10: Mascotas | D10: Evergreen | E10: Pelo en ropa y muebles; fácil de demostrar en video | F10: 11000 | G10: 15000 | H10: 64900 | I10: 0.035 | J10: 0.2 | K10: 30000 | L10: =H10-F10-G10-H10*I10-J10*K10 -> 30628.5 | M10: =IF(H10=0,0,L10/H10) -> 0.47193374 | N10: =MAX(L10,0) -> 30628.5 | O10: =IF(L10<=0,"Sin margen",H10/L10) -> 2.1189415 | P10: 19000 | Q10: =P10*(1+Plan_100K!$B$5) -> 30400 | R10: =L10-Q10 -> 228.5 | S10: =IF(H10=0,0,R10/H10) -> 0.0035208012 | T10: =IF(R10<=0,"NO: pierde dinero",IF(S10>=0.15,"SÍ: probar con fuerza","Probar con cuidado")) -> Probar con cuidado | U10: Sí
A12: SUPUESTOS Y FUENTES (Dropi Colombia):
A13: - Flete $15,000: la guía de Andrey Business (afiliado de Dropi) lista fletes contra entrega de $12,100 urbano, $13,800 regional y $15,700 nacional; varía con la transportadora y puede ser el doble en pueblos pequeños. Verifica en el simulador de tu panel Dropi.
A14: - Comisión de recaudo 3.5%: dos fuentes difieren (3.5% o 2-3%). Confírmalo con Dropi.
A15: - Devolución: si el pedido regresa pierdes el flete de ida y de vuelta (por eso $30,000). El 20% de devoluciones es supuesto mío: usa tu tasa real.
A16: - CPA = costo por venta en anuncios. Alza de 60% en Q4 (Plan_100K!B5): el blog Copyfy habla de 40-80% en noviembre.
A17: - Precios de producto, de venta y CPA base: estimaciones mías, no datos de Dropi.

Sheet Plan_100K
A1: Plan para llegar a la meta de ventas (en COP)
A2: Cuánto gastarías en producto, fletes, comisiones, devoluciones y publicidad para vender la meta en Q4.
A4: Meta de ventas (USD) | B4: 100000 | C4: Tu objetivo en dólares
A5: Alza del costo de publicidad en Q4 % | B5: 0.6 | C5: Supuesto: entre 40% y 80% (blog Copyfy)
A6: Otros costos fijos totales (apps, dominio, herramientas) COP | B6: 2000000 | C6: Supuesto mío, ~$650,000 al mes
A7: Fecha de inicio | B7: 46307 | C7: Hoy
A8: Fecha límite de la meta | B8: 46387 | C8: Fin de año
A9: Tasa de cambio TRM (COP por USD) | B9: 3200 | C9: TRM del 7 oct 2026: $3,216 (Portafolio). Actualiza con la del día.
A10: META DE VENTAS EN PESOS (COP) | B10: =B4*B9 -> 320000000 | C10: Meta en USD x TRM
A12: Producto | B12: % de la meta (mezcla de ventas) | C12: Ingresos meta (COP) | D12: Precio venta | E12: Unidades a vender | F12: Costo de producto | G12: Fletes | H12: Comisión de recaudo | I12: Devoluciones | J12: Publicidad (CPA Q4) | K12: Utilidad neta | L12: Margen neto %
A13: =Candidatos!B6 -> Proyector de galaxia / estrellas LED | B13: 0.25 | C13: =$B$10*B13 -> 80000000 | D13: =Candidatos!H6 -> 109900 | E13: =IF(D13=0,0,C13/D13) -> 727.93449 | F13: =E13*Candidatos!F6 -> 21110100 | G13: =E13*Candidatos!G6 -> 10919017 | H13: =C13*Candidatos!I6 -> 2800000 | I13: =E13*Candidatos!J6*Candidatos!K6 -> 4367606.9 | J13: =E13*Candidatos!Q6 -> 33776160 | K13: =C13-F13-G13-H13-I13-J13 -> 7027115.6 | L13: =IF(C13=0,0,K13/C13) -> 0.087838944
A14: =Candidatos!B7 -> Masajeador de cuello / espalda (EMS) | B14: 0.25 | C14: =$B$10*B14 -> 80000000 | D14: =Candidatos!H7 -> 129900 | E14: =IF(D14=0,0,C14/D14) -> 615.85835 | F14: =E14*Candidatos!F7 -> 21555042 | G14: =E14*Candidatos!G7 -> 9237875.3 | H14: =C14*Candidatos!I7 -> 2800000 | I14: =E14*Candidatos!J7*Candidatos!K7 -> 3695150.1 | J14: =E14*Candidatos!Q7 -> 34488068 | K14: =C14-F14-G14-H14-I14-J14 -> 8223864.5 | L14: =IF(C14=0,0,K14/C14) -> 0.10279831
A15: =Candidatos!B8 -> Audífonos Bluetooth (TWS) | B15: 0.2 | C15: =$B$10*B15 -> 64000000 | D15: =Candidatos!H8 -> 94900 | E15: =IF(D15=0,0,C15/D15) -> 674.3941 | F15: =E15*Candidatos!F8 -> 17534247 | G15: =E15*Candidatos!G8 -> 10115911 | H15: =C15*Candidatos!I8 -> 2240000 | I15: =E15*Candidatos!J8*Candidatos!K8 -> 4046364.6 | J15: =E15*Candidatos!Q8 -> 34528978 | K15: =C15-F15-G15-H15-I15-J15 -> -4465500.5 | L15: =IF(C15=0,0,K15/C15) -> -0.069773446
A16: =Candidatos!B9 -> Kit facial gua sha + rodillo + limpiador | B16: 0.15 | C16: =$B$10*B16 -> 48000000 | D16: =Candidatos!H9 -> 79900 | E16: =IF(D16=0,0,C16/D16) -> 600.75094 | F16: =E16*Candidatos!F9 -> 9612015 | G16: =E16*Candidatos!G9 -> 9011264.1 | H16: =C16*Candidatos!I9 -> 1680000 | I16: =E16*Candidatos!J9*Candidatos!K9 -> 3604505.6 | J16: =E16*Candidatos!Q9 -> 21146433 | K16: =C16-F16-G16-H16-I16-J16 -> 2945782.2 | L16: =IF(C16=0,0,K16/C16) -> 0.061370463
A17: =Candidatos!B10 -> Cepillo quitapelos autolimpiante mascotas | B17: 0.15 | C17: =$B$10*B17 -> 48000000 | D17: =Candidatos!H10 -> 64900 | E17: =IF(D17=0,0,C17/D17) -> 739.59938 | F17: =E17*Candidatos!F10 -> 8135593.2 | G17: =E17*Candidatos!G10 -> 11093991 | H17: =C17*Candidatos!I10 -> 1680000 | I17: =E17*Candidatos!J10*Candidatos!K10 -> 4437596.3 | J17: =E17*Candidatos!Q10 -> 22483821 | K17: =C17-F17-G17-H17-I17-J17 -> 168998.46 | L17: =IF(C17=0,0,K17/C17) -> 0.0035208012
A18: TOTAL | B18: =SUM(B13:B17) -> 1 | C18: =SUM(C13:C17) -> 320000000 | E18: =SUM(E13:E17) -> 3358.5373 | F18: =SUM(F13:F17) -> 77946997 | G18: =SUM(G13:G17) -> 50378059 | H18: =SUM(H13:H17) -> 11200000 | I18: =SUM(I13:I17) -> 20151224 | J18: =SUM(J13:J17) -> 1.4642346e+08 | K18: =SUM(K13:K17) -> 13900260 | L18: =IF(C18=0,0,K18/C18) -> 0.043438313
A19: Revisa que la mezcla sume 100%.
A21: RESULTADO FINAL
A22: Utilidad neta antes de costos fijos | B22: =K18 -> 13900260
A23: Menos: otros costos fijos | B23: =B6 -> 2000000
A24: UTILIDAD FINAL ESTIMADA (COP) | B24: =B22-B23 -> 11900260
A25: Costos totales (producto+flete+comisión+devol.+publicidad+fijos) | B25: =F18+G18+H18+I18+J18+B6 -> 3.0809974e+08
A26: ROAS global necesario (ventas / publicidad) | B26: =IF(J18=0,0,C18/J18) -> 2.1854421
A28: RITMO NECESARIO
A29: Días disponibles | B29: =MAX(B8-B7,1) -> 80
A30: Ventas por día (COP) | B30: =B10/B29 -> 4000000
A31: Pedidos por día | B31: =E18/B29 -> 41.981716
A32: Publicidad por día (COP) | B32: =J18/B29 -> 1830293.3
A34: CAPITAL QUE ADELANTAS
A35: Publicidad total (lo que pagas antes de cobrar) | B35: =J18 -> 1.4642346e+08
A36: Nota: en Dropi contra entrega normalmente no pagas el producto por adelantado; se descuenta de tu ganancia al entregarse. Confírmalo en tu cuenta Dropi.

Sheet Promociones_Q4
A1: Promociones mes por mes - último trimestre (COP)
A2: Cada promo calcula si todavía te deja ganancia después de pagar publicidad. En 'Producto' escribe el número 1 a 5 de la hoja Candidatos.
A4: Fecha | B4: Mes | C4: Evento | D4: Promoción sugerida | E4: Producto (1-5) | F4: Descuento % | G4: Precio con promo | H4: Utilidad antes de publicidad | I4: Margen % | J4: CPA Q4 del producto | K4: Utilidad neta | L4: ¿Conviene?
A5: 46326 | B5: Octubre | C5: Halloween | D5: Envío gratis en el primer pedido (sin bajar el precio) | E5: 5 | F5: 0 | G5: =INDEX(Candidatos!$H$6:$H$10,E5)*(1-F5) -> 64900 | H5: =G5-INDEX(Candidatos!$F$6:$F$10,E5)-INDEX(Candidatos!$G$6:$G$10,E5)-G5*INDEX(Candidatos!$I$6:$I$10,E5)-INDEX(Candidatos!$J$6:$J$10,E5)*INDEX(Candidatos!$K$6:$K$10,E5) -> 30628.5 | I5: =IF(G5=0,0,H5/G5) -> 0.47193374 | J5: =INDEX(Candidatos!$Q$6:$Q$10,E5) -> 30400 | K5: =H5-J5 -> 228.5 | L5: =IF(K5<=0,"NO: pierdes dinero",IF(K5/G5>=0.08,"SÍ","Justo: solo para captar clientes")) -> Justo: solo para captar clientes
A6: 46337 | B6: Noviembre | C6: Día de los Solteros (11.11) | D6: Descuento de 1 día con cuenta regresiva | E6: 4 | F6: 0.05 | G6: =INDEX(Candidatos!$H$6:$H$10,E6)*(1-F6) -> 75905 | H6: =G6-INDEX(Candidatos!$F$6:$F$10,E6)-INDEX(Candidatos!$G$6:$G$10,E6)-G6*INDEX(Candidatos!$I$6:$I$10,E6)-INDEX(Candidatos!$J$6:$J$10,E6)*INDEX(Candidatos!$K$6:$K$10,E6) -> 36248.325 | I6: =IF(G6=0,0,H6/G6) -> 0.47754858 | J6: =INDEX(Candidatos!$Q$6:$Q$10,E6) -> 35200 | K6: =H6-J6 -> 1048.325 | L6: =IF(K6<=0,"NO: pierdes dinero",IF(K6/G6>=0.08,"SÍ","Justo: solo para captar clientes")) -> Justo: solo para captar clientes
A7: 46346 | B7: Noviembre | C7: Pre-Black Friday | D7: Lista VIP por WhatsApp: acceso anticipado + regalo | E7: 2 | F7: 0.05 | G7: =INDEX(Candidatos!$H$6:$H$10,E7)*(1-F7) -> 123405 | H7: =G7-INDEX(Candidatos!$F$6:$F$10,E7)-INDEX(Candidatos!$G$6:$G$10,E7)-G7*INDEX(Candidatos!$I$6:$I$10,E7)-INDEX(Candidatos!$J$6:$J$10,E7)*INDEX(Candidatos!$K$6:$K$10,E7) -> 63085.825 | I7: =IF(G7=0,0,H7/G7) -> 0.51120963 | J7: =INDEX(Candidatos!$Q$6:$Q$10,E7) -> 56000 | K7: =H7-J7 -> 7085.825 | L7: =IF(K7<=0,"NO: pierdes dinero",IF(K7/G7>=0.08,"SÍ","Justo: solo para captar clientes")) -> Justo: solo para captar clientes
A8: 46353 | B8: Noviembre | C8: Black Friday | D8: Oferta relámpago 24 h + regalo sorpresa (no bajes de 10%) | E8: 2 | F8: 0.1 | G8: =INDEX(Candidatos!$H$6:$H$10,E8)*(1-F8) -> 116910 | H8: =G8-INDEX(Candidatos!$F$6:$F$10,E8)-INDEX(Candidatos!$G$6:$G$10,E8)-G8*INDEX(Candidatos!$I$6:$I$10,E8)-INDEX(Candidatos!$J$6:$J$10,E8)*INDEX(Candidatos!$K$6:$K$10,E8) -> 56818.15 | I8: =IF(G8=0,0,H8/G8) -> 0.48599906 | J8: =INDEX(Candidatos!$Q$6:$Q$10,E8) -> 56000 | K8: =H8-J8 -> 818.15 | L8: =IF(K8<=0,"NO: pierdes dinero",IF(K8/G8>=0.08,"SÍ","Justo: solo para captar clientes")) -> Justo: solo para captar clientes
A9: 46356 | B9: Noviembre | C9: Cyber Monday | D9: Última oportunidad: misma oferta con envío garantizado | E9: 1 | F9: 0.05 | G9: =INDEX(Candidatos!$H$6:$H$10,E9)*(1-F9) -> 104405 | H9: =G9-INDEX(Candidatos!$F$6:$F$10,E9)-INDEX(Candidatos!$G$6:$G$10,E9)-G9*INDEX(Candidatos!$I$6:$I$10,E9)-INDEX(Candidatos!$J$6:$J$10,E9)*INDEX(Candidatos!$K$6:$K$10,E9) -> 50750.825 | I9: =IF(G9=0,0,H9/G9) -> 0.48609573 | J9: =INDEX(Candidatos!$Q$6:$Q$10,E9) -> 46400 | K9: =H9-J9 -> 4350.825 | L9: =IF(K9<=0,"NO: pierdes dinero",IF(K9/G9>=0.08,"SÍ","Justo: solo para captar clientes")) -> Justo: solo para captar clientes
A10: 46370 | B10: Diciembre | C10: Green Monday | D10: Regalo doble (producto + accesorio barato) | E10: 2 | F10: 0 | G10: =INDEX(Candidatos!$H$6:$H$10,E10)*(1-F10) -> 129900 | H10: =G10-INDEX(Candidatos!$F$6:$F$10,E10)-INDEX(Candidatos!$G$6:$G$10,E10)-G10*INDEX(Candidatos!$I$6:$I$10,E10)-INDEX(Candidatos!$J$6:$J$10,E10)*INDEX(Candidatos!$K$6:$K$10,E10) -> 69353.5 | I10: =IF(G10=0,0,H10/G10) -> 0.53389915 | J10: =INDEX(Candidatos!$Q$6:$Q$10,E10) -> 56000 | K10: =H10-J10 -> 13353.5 | L10: =IF(K10<=0,"NO: pierdes dinero",IF(K10/G10>=0.08,"SÍ","Justo: solo para captar clientes")) -> SÍ
A11: 46374 | B11: Diciembre | C11: Último día de entrega navideña | D11: Urgencia: 'pídelo hoy y llega antes de Navidad' | E11: 2 | F11: 0 | G11: =INDEX(Candidatos!$H$6:$H$10,E11)*(1-F11) -> 129900 | H11: =G11-INDEX(Candidatos!$F$6:$F$10,E11)-INDEX(Candidatos!$G$6:$G$10,E11)-G11*INDEX(Candidatos!$I$6:$I$10,E11)-INDEX(Candidatos!$J$6:$J$10,E11)*INDEX(Candidatos!$K$6:$K$10,E11) -> 69353.5 | I11: =IF(G11=0,0,H11/G11) -> 0.53389915 | J11: =INDEX(Candidatos!$Q$6:$Q$10,E11) -> 56000 | K11: =H11-J11 -> 13353.5 | L11: =IF(K11<=0,"NO: pierdes dinero",IF(K11/G11>=0.08,"SÍ","Justo: solo para captar clientes")) -> SÍ
A12: 46384 | B12: Diciembre | C12: Post-Navidad / Año Nuevo | D12: Propósitos de año nuevo: casa limpia y cuidado personal | E12: 5 | F12: 0 | G12: =INDEX(Candidatos!$H$6:$H$10,E12)*(1-F12) -> 64900 | H12: =G12-INDEX(Candidatos!$F$6:$F$10,E12)-INDEX(Candidatos!$G$6:$G$10,E12)-G12*INDEX(Candidatos!$I$6:$I$10,E12)-INDEX(Candidatos!$J$6:$J$10,E12)*INDEX(Candidatos!$K$6:$K$10,E12) -> 30628.5 | I12: =IF(G12=0,0,H12/G12) -> 0.47193374 | J12: =INDEX(Candidatos!$Q$6:$Q$10,E12) -> 30400 | K12: =H12-J12 -> 228.5 | L12: =IF(K12<=0,"NO: pierdes dinero",IF(K12/G12>=0.08,"SÍ","Justo: solo para captar clientes")) -> Justo: solo para captar clientes
A13: Black Friday (27 nov) y Cyber Monday (30 nov) 2026: fechas del blog Copyfy; confirma el calendario en Colombia.
A15: COMBOS (la forma más segura de subir la ganancia por pedido)
A16: Producto (1-5) | B16: Unidades en el combo | D16: Precio del combo | E16: Costo producto | F16: Flete del combo | G16: Comisión recaudo | H16: Devoluciones esperadas | I16: Utilidad antes de publicidad | J16: CPA Q4 | K16: Utilidad neta | L16: Margen neto %
A17: 5 | B17: 2 | D17: 119900 | E17: =INDEX(Candidatos!$F$6:$F$10,A17)*B17 -> 22000 | F17: 18000 | G17: =D17*INDEX(Candidatos!$I$6:$I$10,A17) -> 4196.5 | H17: =INDEX(Candidatos!$J$6:$J$10,A17)*(F17*2) -> 7200 | I17: =D17-E17-F17-G17-H17 -> 68503.5 | J17: =INDEX(Candidatos!$Q$6:$Q$10,A17) -> 30400 | K17: =I17-J17 -> 38103.5 | L17: =IF(D17=0,0,K17/D17) -> 0.31779399
A18: 2 | B18: 2 | D18: 239900 | E18: =INDEX(Candidatos!$F$6:$F$10,A18)*B18 -> 70000 | F18: 19000 | G18: =D18*INDEX(Candidatos!$I$6:$I$10,A18) -> 8396.5 | H18: =INDEX(Candidatos!$J$6:$J$10,A18)*(F18*2) -> 7600 | I18: =D18-E18-F18-G18-H18 -> 134903.5 | J18: =INDEX(Candidatos!$Q$6:$Q$10,A18) -> 56000 | K18: =I18-J18 -> 78903.5 | L18: =IF(D18=0,0,K18/D18) -> 0.32890163
A19: 1 | B19: 2 | D19: 199900 | E19: =INDEX(Candidatos!$F$6:$F$10,A19)*B19 -> 58000 | F19: 18000 | G19: =D19*INDEX(Candidatos!$I$6:$I$10,A19) -> 6996.5 | H19: =INDEX(Candidatos!$J$6:$J$10,A19)*(F19*2) -> 7200 | I19: =D19-E19-F19-G19-H19 -> 109703.5 | J19: =INDEX(Candidatos!$Q$6:$Q$10,A19) -> 46400 | K19: =I19-J19 -> 63303.5 | L19: =IF(D19=0,0,K19/D19) -> 0.31667584
A20: Flete del combo ($18,000-19,000) es supuesto mío: un pedido de 2 unidades suele costar más que uno de 1. Confírmalo con el simulador de Dropi.

Sheet Como_validar
A1: Cómo validar cada producto y llegar a la meta
A2: Antes de gastar en anuncios, que el producto pase estas pruebas.
A4: PRUEBAS ANTES DE COMPRAR PUBLICIDAD
A5: 1. Stock en Dropi | B5: Que tenga stock suficiente y varios proveedores.
A6: 2. Tasa de entrega | B6: Pregunta a Dropi por la tasa de entrega por ciudad. Si es menor a 75%, sube el % de devolución en Candidatos.
A7: 3. Flete real | B7: Usa el simulador de fletes de tu panel Dropi con tus ciudades más comunes y pon ese valor en la columna Flete.
A8: 4. Competencia | B8: Revisa la Biblioteca de Anuncios de Meta y el Creative Center de TikTok: mucha gente anunciando hace meses = funciona pero está saturado.
A9: 5. Margen | B9: La hoja Candidatos debe decir 'SÍ' con tus costos reales. Si dice 'NO', descártalo aunque sea viral.
A10: 6. Prueba pequeña | B10: Gasta 2 a 3 veces tu CPA máximo por producto y escala solo los de buen ROAS.
A11: MES POR MES
A12: Octubre | B12: Valida los productos con pruebas pequeñas, crea páginas y videos, y arma la lista de WhatsApp.
A13: Noviembre | B13: 11.11, pre-Black Friday, Black Friday y Cyber Monday: usa combos y regalos antes que descuentos grandes.
A14: Diciembre | B14: Regalos y urgencia de entrega hasta el 18-20 dic. Después detén productos que no lleguen a tiempo.
A15: AVISO | B15: El plan calcula lo que necesitarías para la meta, no la garantiza. Con estos supuestos el margen es bajo.
