Workbook

Sheet Candidatos
A1: 5 productos candidatos - Q4 2026
A2: HIPÓTESIS a validar: los costos Dropi, fletes y precios son SUPUESTOS míos. Cámbialos (amarillo) por los reales de tu catálogo Dropi.
A3: Importante: no tuve acceso al catálogo de Dropi ni a datos de ventas en vivo. Las categorías salen de tendencias de Q4 publicadas; el producto exacto lo eliges tú en Dropi (ver hoja Cómo validar).
A5: # | B5: Producto (tipo a buscar en Dropi) | C5: Categoría | D5: Tipo | E5: Por qué en Q4 | F5: Costo Dropi (USD) | G5: Flete (USD) | H5: Precio venta (USD) | I5: Comisión pasarela % | J5: % devolución / no entrega | K5: Costo por devolución (USD) | L5: Utilidad antes de publicidad | M5: Margen % | N5: CPA máximo | O5: ROAS mínimo | P5: CPA base esperado (USD) | Q5: CPA Q4 (con alza) | R5: Utilidad neta por venta | S5: Margen neto % | T5: Veredicto
A6: 1 | B6: Proyector de galaxia / estrellas LED | C6: Hogar / regalo | D6: Viral | E6: Regalo visual, muy grabable en TikTok; sube en Navidad | F6: 9 | G6: 4.5 | H6: 34.99 | I6: 0.04 | J6: 0.15 | K6: 4.5 | L6: =H6-F6-G6-H6*I6-J6*K6 -> 19.4154 | M6: =IF(H6=0,0,L6/H6) -> 0.55488425 | N6: =MAX(L6,0) -> 19.4154 | O6: =IF(L6<=0,"Sin margen",H6/L6) -> 1.8021777 | P6: 9 | Q6: =P6*(1+Plan_100K!$B$5) -> 14.4 | R6: =L6-Q6 -> 5.0154 | S6: =IF(H6=0,0,R6/H6) -> 0.1433381 | T6: =IF(R6<=0,"NO: pierde dinero",IF(S6>=0.15,"SÍ: probar con fuerza","Probar con cuidado")) -> Probar con cuidado
A7: 2 | B7: Masajeador de cuello / espalda (EMS) | C7: Salud y bienestar | D7: Viral | E7: Regalo de Navidad y Día del Padre/Madre; demanda de salud | F7: 11 | G7: 4.5 | H7: 39.99 | I7: 0.04 | J7: 0.15 | K7: 4.5 | L7: =H7-F7-G7-H7*I7-J7*K7 -> 22.2154 | M7: =IF(H7=0,0,L7/H7) -> 0.55552388 | N7: =MAX(L7,0) -> 22.2154 | O7: =IF(L7<=0,"Sin margen",H7/L7) -> 1.8001026 | P7: 11 | Q7: =P7*(1+Plan_100K!$B$5) -> 17.6 | R7: =L7-Q7 -> 4.6154 | S7: =IF(H7=0,0,R7/H7) -> 0.11541385 | T7: =IF(R7<=0,"NO: pierde dinero",IF(S7>=0.15,"SÍ: probar con fuerza","Probar con cuidado")) -> Probar con cuidado
A8: 3 | B8: Audífonos Bluetooth (TWS) | C8: Tecnología | D8: Evergreen | E8: Regalo muy buscado en Black Friday; mercado grande pero competido | F8: 8 | G8: 4 | H8: 29.99 | I8: 0.04 | J8: 0.15 | K8: 4 | L8: =H8-F8-G8-H8*I8-J8*K8 -> 16.1904 | M8: =IF(H8=0,0,L8/H8) -> 0.53985995 | N8: =MAX(L8,0) -> 16.1904 | O8: =IF(L8<=0,"Sin margen",H8/L8) -> 1.8523322 | P8: 10 | Q8: =P8*(1+Plan_100K!$B$5) -> 16 | R8: =L8-Q8 -> 0.1904 | S8: =IF(H8=0,0,R8/H8) -> 0.0063487829 | T8: =IF(R8<=0,"NO: pierde dinero",IF(S8>=0.15,"SÍ: probar con fuerza","Probar con cuidado")) -> Probar con cuidado
A9: 4 | B9: Kit facial gua sha + rodillo + limpiador | C9: Belleza | D9: Viral | E9: Belleza/cuidado personal como regalo; videos antes/después | F9: 5 | G9: 4 | H9: 24.99 | I9: 0.04 | J9: 0.15 | K9: 4 | L9: =H9-F9-G9-H9*I9-J9*K9 -> 14.3904 | M9: =IF(H9=0,0,L9/H9) -> 0.57584634 | N9: =MAX(L9,0) -> 14.3904 | O9: =IF(L9<=0,"Sin margen",H9/L9) -> 1.7365744 | P9: 7 | Q9: =P9*(1+Plan_100K!$B$5) -> 11.2 | R9: =L9-Q9 -> 3.1904 | S9: =IF(H9=0,0,R9/H9) -> 0.12766707 | T9: =IF(R9<=0,"NO: pierde dinero",IF(S9>=0.15,"SÍ: probar con fuerza","Probar con cuidado")) -> Probar con cuidado
A10: 5 | B10: Cepillo quitapelos autolimpiante mascotas | C10: Mascotas | D10: Evergreen | E10: Mascotas es nicho estable; fácil de demostrar en video | F10: 3.5 | G10: 4 | H10: 19.99 | I10: 0.04 | J10: 0.15 | K10: 4 | L10: =H10-F10-G10-H10*I10-J10*K10 -> 11.0904 | M10: =IF(H10=0,0,L10/H10) -> 0.5547974 | N10: =MAX(L10,0) -> 11.0904 | O10: =IF(L10<=0,"Sin margen",H10/L10) -> 1.8024598 | P10: 6 | Q10: =P10*(1+Plan_100K!$B$5) -> 9.6 | R10: =L10-Q10 -> 1.4904 | S10: =IF(H10=0,0,R10/H10) -> 0.074557279 | T10: =IF(R10<=0,"NO: pierde dinero",IF(S10>=0.15,"SÍ: probar con fuerza","Probar con cuidado")) -> Probar con cuidado
A12: Cómo leerla: 'Utilidad antes de publicidad' = precio - costo - flete - comisión - devoluciones esperadas.
A13: CPA máximo = lo más que puedes pagar en anuncios por venta sin perder. CPA Q4 = CPA base subido por el alza de costos de anuncios en noviembre (se cambia en Plan_100K!B5).
A14: Fuente del alza: Copyfy indica que los costos de publicidad suben 40-80% en noviembre (blog de un proveedor; úsalo como referencia, no como dato exacto).
A15: % de devolución 15%: supuesto mío para contra entrega (COD). Revisa tu tasa real de entrega con tu transportadora/Dropi.
A16: Todo en USD. Si Dropi te cobra en pesos, convierte con la tasa del día.

Sheet Plan_100K
A1: Plan para llegar a $100,000 en ventas
A2: Cuánto gastarías en producto, fletes, comisiones, devoluciones y publicidad para vender la meta en Q4.
A4: Meta de ventas (USD) | B4: 100000 | C4: Tu objetivo
A5: Alza del costo de publicidad en Q4 % | B5: 0.6 | C5: Supuesto: entre 40% y 80% (fuente: blog Copyfy)
A6: Otros costos fijos totales (apps, dominio, herramientas) | B6: 600 | C6: Supuesto mío ~ $200/mes x 3 meses
A7: Fecha de inicio | B7: 46307 | C7: Hoy
A8: Fecha límite de la meta | B8: 46387 | C8: Fin de año
A10: Producto | B10: % de la meta (mezcla de ventas) | C10: Ingresos meta | D10: Precio venta | E10: Unidades a vender | F10: Costo de producto | G10: Fletes | H10: Comisiones pasarela | I10: Devoluciones | J10: Publicidad (CPA Q4) | K10: Utilidad neta | L10: Margen neto %
A11: =Candidatos!B6 -> Proyector de galaxia / estrellas LED | B11: 0.25 | C11: =$B$4*B11 -> 25000 | D11: =Candidatos!H6 -> 34.99 | E11: =IF(D11=0,0,C11/D11) -> 714.48985 | F11: =E11*Candidatos!F6 -> 6430.4087 | G11: =E11*Candidatos!G6 -> 3215.2043 | H11: =C11*Candidatos!I6 -> 1000 | I11: =E11*Candidatos!J6*Candidatos!K6 -> 482.28065 | J11: =E11*Candidatos!Q6 -> 10288.654 | K11: =C11-F11-G11-H11-I11-J11 -> 3583.4524 | L11: =IF(C11=0,0,K11/C11) -> 0.1433381
A12: =Candidatos!B7 -> Masajeador de cuello / espalda (EMS) | B12: 0.25 | C12: =$B$4*B12 -> 25000 | D12: =Candidatos!H7 -> 39.99 | E12: =IF(D12=0,0,C12/D12) -> 625.15629 | F12: =E12*Candidatos!F7 -> 6876.7192 | G12: =E12*Candidatos!G7 -> 2813.2033 | H12: =C12*Candidatos!I7 -> 1000 | I12: =E12*Candidatos!J7*Candidatos!K7 -> 421.9805 | J12: =E12*Candidatos!Q7 -> 11002.751 | K12: =C12-F12-G12-H12-I12-J12 -> 2885.3463 | L12: =IF(C12=0,0,K12/C12) -> 0.11541385
A13: =Candidatos!B8 -> Audífonos Bluetooth (TWS) | B13: 0.2 | C13: =$B$4*B13 -> 20000 | D13: =Candidatos!H8 -> 29.99 | E13: =IF(D13=0,0,C13/D13) -> 666.88896 | F13: =E13*Candidatos!F8 -> 5335.1117 | G13: =E13*Candidatos!G8 -> 2667.5559 | H13: =C13*Candidatos!I8 -> 800 | I13: =E13*Candidatos!J8*Candidatos!K8 -> 400.13338 | J13: =E13*Candidatos!Q8 -> 10670.223 | K13: =C13-F13-G13-H13-I13-J13 -> 126.97566 | L13: =IF(C13=0,0,K13/C13) -> 0.0063487829
A14: =Candidatos!B9 -> Kit facial gua sha + rodillo + limpiador | B14: 0.15 | C14: =$B$4*B14 -> 15000 | D14: =Candidatos!H9 -> 24.99 | E14: =IF(D14=0,0,C14/D14) -> 600.2401 | F14: =E14*Candidatos!F9 -> 3001.2005 | G14: =E14*Candidatos!G9 -> 2400.9604 | H14: =C14*Candidatos!I9 -> 600 | I14: =E14*Candidatos!J9*Candidatos!K9 -> 360.14406 | J14: =E14*Candidatos!Q9 -> 6722.6891 | K14: =C14-F14-G14-H14-I14-J14 -> 1915.006 | L14: =IF(C14=0,0,K14/C14) -> 0.12766707
A15: =Candidatos!B10 -> Cepillo quitapelos autolimpiante mascotas | B15: 0.15 | C15: =$B$4*B15 -> 15000 | D15: =Candidatos!H10 -> 19.99 | E15: =IF(D15=0,0,C15/D15) -> 750.37519 | F15: =E15*Candidatos!F10 -> 2626.3132 | G15: =E15*Candidatos!G10 -> 3001.5008 | H15: =C15*Candidatos!I10 -> 600 | I15: =E15*Candidatos!J10*Candidatos!K10 -> 450.22511 | J15: =E15*Candidatos!Q10 -> 7203.6018 | K15: =C15-F15-G15-H15-I15-J15 -> 1118.3592 | L15: =IF(C15=0,0,K15/C15) -> 0.074557279
A16: TOTAL | B16: =SUM(B11:B15) -> 1 | C16: =SUM(C11:C15) -> 100000 | E16: =SUM(E11:E15) -> 3357.1504 | F16: =SUM(F11:F15) -> 24269.753 | G16: =SUM(G11:G15) -> 14098.425 | H16: =SUM(H11:H15) -> 4000 | I16: =SUM(I11:I15) -> 2114.7637 | J16: =SUM(J11:J15) -> 45887.919 | K16: =SUM(K11:K15) -> 9629.1396 | L16: =IF(C16=0,0,K16/C16) -> 0.096291396
A17: Revisa que la mezcla sume 100%.
A19: RESULTADO FINAL
A20: Utilidad neta antes de costos fijos | B20: =K16 -> 9629.1396
A21: Menos: otros costos fijos | B21: =B6 -> 600
A22: UTILIDAD FINAL ESTIMADA | B22: =B20-B21 -> 9029.1396
A23: Costos totales (producto+flete+comisión+devol.+publicidad+fijos) | B23: =F16+G16+H16+I16+J16+B6 -> 90970.86
A24: ROAS global necesario (ventas / publicidad) | B24: =IF(J16=0,0,C16/J16) -> 2.1792228
A25: RITMO NECESARIO
A26: Días disponibles | B26: =MAX(B8-B7,1) -> 80
A27: Ventas por día (USD) | B27: =B4/B26 -> 1250
A28: Pedidos por día | B28: =E16/B26 -> 41.96438
A29: Publicidad por día (USD) | B29: =J16/B26 -> 573.59899
A30: Capital que necesitas adelantar
A31: Publicidad total (lo principal que pagas antes de cobrar) | B31: =J16 -> 45887.919
A32: Nota | B32: En Dropi con contra entrega normalmente no pagas el producto por adelantado: se descuenta de tu ganancia cuando se entrega. Confírmalo con tu cuenta Dropi.

Sheet Promociones_Q4
A1: Calendario de promociones - último trimestre
A2: Cada promo calcula si todavía te deja ganancia después de pagar publicidad. Cambia el producto y el descuento (amarillo).
A4: Fecha | B4: Evento | C4: Promoción sugerida | D4: Producto | E4: Descuento % | F4: Precio con promo | G4: Utilidad antes de publicidad | H4: Margen % | I4: CPA Q4 del producto | J4: Utilidad neta | K4: ¿Conviene?
A5: 46326 | B5: Halloween | C5: Combo 'Noche de terror': compra 1 y recibe envío gratis | D5: 1 | E5: 0.1 | F5: =INDEX(Candidatos!$H$6:$H$10,D5)*(1-E5) -> 31.491 | G5: =F5-INDEX(Candidatos!$F$6:$F$10,D5)-INDEX(Candidatos!$G$6:$G$10,D5)-F5*INDEX(Candidatos!$I$6:$I$10,D5)-INDEX(Candidatos!$J$6:$J$10,D5)*INDEX(Candidatos!$K$6:$K$10,D5) -> 16.05636 | H5: =IF(F5=0,0,G5/F5) -> 0.50987139 | I5: =INDEX(Candidatos!$Q$6:$Q$10,D5) -> 14.4 | J5: =G5-I5 -> 1.65636 | K5: =IF(J5<=0,"NO: pierdes dinero",IF(J5/F5>=0.1,"SÍ","Justo: úsala solo para captar clientes")) -> Justo: úsala solo para captar clientes
A6: 46337 | B6: Día de los Solteros (11.11) | C6: 11% de descuento solo ese día + cuenta regresiva | D6: 4 | E6: 0.11 | F6: =INDEX(Candidatos!$H$6:$H$10,D6)*(1-E6) -> 22.2411 | G6: =F6-INDEX(Candidatos!$F$6:$F$10,D6)-INDEX(Candidatos!$G$6:$G$10,D6)-F6*INDEX(Candidatos!$I$6:$I$10,D6)-INDEX(Candidatos!$J$6:$J$10,D6)*INDEX(Candidatos!$K$6:$K$10,D6) -> 11.751456 | H6: =IF(F6=0,0,G6/F6) -> 0.52836667 | I6: =INDEX(Candidatos!$Q$6:$Q$10,D6) -> 11.2 | J6: =G6-I6 -> 0.551456 | K6: =IF(J6<=0,"NO: pierdes dinero",IF(J6/F6>=0.1,"SÍ","Justo: úsala solo para captar clientes")) -> Justo: úsala solo para captar clientes
A7: 46346 | B7: Pre-Black Friday | C7: Lista VIP por WhatsApp: acceso anticipado con 10% extra | D7: 2 | E7: 0.1 | F7: =INDEX(Candidatos!$H$6:$H$10,D7)*(1-E7) -> 35.991 | G7: =F7-INDEX(Candidatos!$F$6:$F$10,D7)-INDEX(Candidatos!$G$6:$G$10,D7)-F7*INDEX(Candidatos!$I$6:$I$10,D7)-INDEX(Candidatos!$J$6:$J$10,D7)*INDEX(Candidatos!$K$6:$K$10,D7) -> 18.37636 | H7: =IF(F7=0,0,G7/F7) -> 0.51058209 | I7: =INDEX(Candidatos!$Q$6:$Q$10,D7) -> 17.6 | J7: =G7-I7 -> 0.77636 | K7: =IF(J7<=0,"NO: pierdes dinero",IF(J7/F7>=0.1,"SÍ","Justo: úsala solo para captar clientes")) -> Justo: úsala solo para captar clientes
A8: 46353 | B8: Black Friday | C8: Oferta relámpago 24 h + regalo sorpresa (producto barato de Dropi) | D8: 1 | E8: 0.2 | F8: =INDEX(Candidatos!$H$6:$H$10,D8)*(1-E8) -> 27.992 | G8: =F8-INDEX(Candidatos!$F$6:$F$10,D8)-INDEX(Candidatos!$G$6:$G$10,D8)-F8*INDEX(Candidatos!$I$6:$I$10,D8)-INDEX(Candidatos!$J$6:$J$10,D8)*INDEX(Candidatos!$K$6:$K$10,D8) -> 12.69732 | H8: =IF(F8=0,0,G8/F8) -> 0.45360532 | I8: =INDEX(Candidatos!$Q$6:$Q$10,D8) -> 14.4 | J8: =G8-I8 -> -1.70268 | K8: =IF(J8<=0,"NO: pierdes dinero",IF(J8/F8>=0.1,"SÍ","Justo: úsala solo para captar clientes")) -> NO: pierdes dinero
A9: 46356 | B9: Cyber Monday | C9: Última oportunidad: mismo descuento con envío rápido | D9: 3 | E9: 0.15 | F9: =INDEX(Candidatos!$H$6:$H$10,D9)*(1-E9) -> 25.4915 | G9: =F9-INDEX(Candidatos!$F$6:$F$10,D9)-INDEX(Candidatos!$G$6:$G$10,D9)-F9*INDEX(Candidatos!$I$6:$I$10,D9)-INDEX(Candidatos!$J$6:$J$10,D9)*INDEX(Candidatos!$K$6:$K$10,D9) -> 11.87184 | H9: =IF(F9=0,0,G9/F9) -> 0.46571759 | I9: =INDEX(Candidatos!$Q$6:$Q$10,D9) -> 16 | J9: =G9-I9 -> -4.12816 | K9: =IF(J9<=0,"NO: pierdes dinero",IF(J9/F9>=0.1,"SÍ","Justo: úsala solo para captar clientes")) -> NO: pierdes dinero
A10: 46370 | B10: Green Monday | C10: Descuento por volumen: 2da unidad con 25% menos | D10: 5 | E10: 0.15 | F10: =INDEX(Candidatos!$H$6:$H$10,D10)*(1-E10) -> 16.9915 | G10: =F10-INDEX(Candidatos!$F$6:$F$10,D10)-INDEX(Candidatos!$G$6:$G$10,D10)-F10*INDEX(Candidatos!$I$6:$I$10,D10)-INDEX(Candidatos!$J$6:$J$10,D10)*INDEX(Candidatos!$K$6:$K$10,D10) -> 8.21184 | H10: =IF(F10=0,0,G10/F10) -> 0.48329106 | I10: =INDEX(Candidatos!$Q$6:$Q$10,D10) -> 9.6 | J10: =G10-I10 -> -1.38816 | K10: =IF(J10<=0,"NO: pierdes dinero",IF(J10/F10>=0.1,"SÍ","Justo: úsala solo para captar clientes")) -> NO: pierdes dinero
A11: 46374 | B11: Último día de entrega navideña | C11: Urgencia: 'pídelo hoy y llega antes de Navidad' | D11: 2 | E11: 0.1 | F11: =INDEX(Candidatos!$H$6:$H$10,D11)*(1-E11) -> 35.991 | G11: =F11-INDEX(Candidatos!$F$6:$F$10,D11)-INDEX(Candidatos!$G$6:$G$10,D11)-F11*INDEX(Candidatos!$I$6:$I$10,D11)-INDEX(Candidatos!$J$6:$J$10,D11)*INDEX(Candidatos!$K$6:$K$10,D11) -> 18.37636 | H11: =IF(F11=0,0,G11/F11) -> 0.51058209 | I11: =INDEX(Candidatos!$Q$6:$Q$10,D11) -> 17.6 | J11: =G11-I11 -> 0.77636 | K11: =IF(J11<=0,"NO: pierdes dinero",IF(J11/F11>=0.1,"SÍ","Justo: úsala solo para captar clientes")) -> Justo: úsala solo para captar clientes
A12: 46382 | B12: Post-Navidad / Año Nuevo | C12: Liquidación de stock + regalos para 'tu yo del 2027' | D12: 4 | E12: 0.2 | F12: =INDEX(Candidatos!$H$6:$H$10,D12)*(1-E12) -> 19.992 | G12: =F12-INDEX(Candidatos!$F$6:$F$10,D12)-INDEX(Candidatos!$G$6:$G$10,D12)-F12*INDEX(Candidatos!$I$6:$I$10,D12)-INDEX(Candidatos!$J$6:$J$10,D12)*INDEX(Candidatos!$K$6:$K$10,D12) -> 9.59232 | H12: =IF(F12=0,0,G12/F12) -> 0.47980792 | I12: =INDEX(Candidatos!$Q$6:$Q$10,D12) -> 11.2 | J12: =G12-I12 -> -1.60768 | K12: =IF(J12<=0,"NO: pierdes dinero",IF(J12/F12>=0.1,"SÍ","Justo: úsala solo para captar clientes")) -> NO: pierdes dinero
A13: En la columna 'Producto' escribe el número del producto (1 a 5) según la hoja Candidatos.
A14: Fechas de Black Friday (27 nov) y Cyber Monday (30 nov) de 2026 tomadas del blog Copyfy; verifica el calendario de tu país.

Sheet Como_validar
A1: Cómo validar cada producto y llegar a $100K
A2: Antes de gastar en anuncios, que el producto pase estas pruebas.
A4: PRUEBAS ANTES DE COMPRAR PUBLICIDAD
A5: 1. Stock en Dropi | B5: Que tenga stock suficiente (idealmente más de 500 unidades) y varios proveedores.
A6: 2. Tasa de entrega | B6: Pregunta a Dropi/transportadora la tasa de entrega por ciudad. Si es menor a 75%, sube el % de devolución en Candidatos.
A7: 3. Espía a la competencia | B7: Mira la Biblioteca de Anuncios de Meta y TikTok Creative Center: si muchos anuncian el mismo producto hace meses, funciona pero está saturado.
A8: 4. Margen | B8: Que la hoja Candidatos diga 'SÍ' con tu costo real. Si dice 'NO', descártalo aunque sea viral.
A9: 5. Prueba pequeña | B9: Gasta 2-3 veces tu CPA máximo por producto (hoja Publicidad de la otra plantilla). Escala solo los de ROAS alto.
A10: VIRAL vs EVERGREEN
A11: Virales | B11: Venden rápido, pero se saturan en semanas y el costo de anuncio sube. Entra pronto, no compres inventario grande.
A12: Evergreen | B12: Venden estable todo el año y toleran más competencia. Son tu base para no depender de una sola moda.
A13: RUTA SUGERIDA A $100K
A14: Semana 1-2 (oct) | B14: Valida los 5 productos con pruebas pequeñas. Crea las páginas y videos. Quédate con los 2-3 mejores.
A15: Semana 3-4 (fin oct) | B15: Escala lo que funcione 20-30% cada 2-3 días. Empieza la lista de WhatsApp/correo para Black Friday.
A16: Noviembre | B16: Pre-Black Friday, Black Friday, Cyber Monday: es donde se concentra gran parte de las ventas. Prepara anuncios antes de que suba el costo.
A17: Diciembre | B17: Combos y urgencia de entrega hasta el 18-20 dic. Después, liquidación para el siguiente año.
A18: Reglas de oro | B18: Revisa la hoja Plan_100K cada semana: ¿vas por el ritmo diario de ventas? Si el ROAS real queda debajo del ROAS mínimo, pausa.
A19: AVISO | B19: La meta de $100K es ambiciosa para un primer trimestre; el plan calcula lo que necesitarías, no lo garantiza. Mira el ritmo diario en Plan_100K.
